pynvesting/__init__.py
pynvesting/bonds.py
pynvesting/certificates.py
pynvesting/commodities.py
pynvesting/crypto.py
pynvesting/currency_crosses.py
pynvesting/data/__init__.py
pynvesting/data/bonds_data.py
pynvesting/data/certificates_data.py
pynvesting/data/commodities_data.py
pynvesting/data/crypto_data.py
pynvesting/data/currency_crosses_data.py
pynvesting/data/etfs_data.py
pynvesting/data/funds_data.py
pynvesting/data/indices_data.py
pynvesting/data/stocks_data.py
pynvesting/etfs.py
pynvesting/funds.py
pynvesting/indices.py
pynvesting/news.py
pynvesting/resources/bonds.csv
pynvesting/resources/certificates.csv
pynvesting/resources/commodities.csv
pynvesting/resources/cryptos.csv
pynvesting/resources/currency_crosses.csv
pynvesting/resources/etfs.csv
pynvesting/resources/funds.csv
pynvesting/resources/indices.csv
pynvesting/resources/stocks.csv
pynvesting/search.py
pynvesting/stocks.py
pynvesting/technical.py
pynvesting/utils/__init__.py
pynvesting/utils/constant.py
pynvesting/utils/data.py
pynvesting/utils/extra.py
pynvesting/utils/search_obj.py
pynvesting-0.1.0.dist-info/LICENSE
pynvesting-0.1.0.dist-info/METADATA
pynvesting-0.1.0.dist-info/WHEEL
pynvesting-0.1.0.dist-info/RECORD
