Metadata-Version: 2.3
Name: pynvesting
Version: 0.1.0
Summary: Scraper de dados do site Investing.com
License: MIT
Author: Marco Antonio Rodrigues Gomes de Souza
Author-email: 94053824+Marco-Antonio-Rodrigues@users.noreply.github.com
Requires-Python: >=3.10
Classifier: License :: OSI Approved :: MIT License
Classifier: Programming Language :: Python :: 3
Classifier: Programming Language :: Python :: 3.10
Classifier: Programming Language :: Python :: 3.11
Classifier: Programming Language :: Python :: 3.12
Classifier: Programming Language :: Python :: 3.13
Requires-Dist: cloudscraper (>=1.2.71,<2.0.0)
Requires-Dist: lxml (>=5.4.0,<6.0.0)
Requires-Dist: pandas (>=2.3.0,<3.0.0)
Requires-Dist: setuptools (>=80.9.0,<81.0.0)
Requires-Dist: unidecode (>=1.4.0,<2.0.0)
Project-URL: Documentation, https://github.com/Marco-Antonio-Rodrigues/pynvesting
Project-URL: Homepage, https://github.com/Marco-Antonio-Rodrigues/pynvesting
Project-URL: Repository, https://github.com/Marco-Antonio-Rodrigues/pynvesting
